[{"ad_id":"120249962126230363","ad_name":"sale_promotion","adset_name":"25-55_여성_전국","age_bracket":"65+","campaign_name":"8LF_ASC_Detail_26.07.10","click_cvr_pct":null,"clicks":"0","cpa_krw":null,"cpc_krw":null,"cpm_krw":"3.0375E7","ctr_pct":"0.0","event_date":"2026-07-22","gender":"male","impressions":"6","purchases":"0","reach":"5","revenue":"0.0","roas":"0.0","spend_krw":"182250.0"},{"ad_id":"120249962126230363","ad_name":"sale_promotion","adset_name":"25-55_여성_전국","age_bracket":"65+","campaign_name":"8LF_ASC_Detail_26.07.10","click_cvr_pct":null,"clicks":"0","cpa_krw":null,"cpc_krw":null,"cpm_krw":"1.053E8","ctr_pct":"0.0","event_date":"2026-07-22","gender":"female","impressions":"3","purchases":"0","reach":"3","revenue":"0.0","roas":"0.0","spend_krw":"315900.0"},{"ad_id":"120249962126230363","ad_name":"sale_promotion","adset_name":"25-55_여성_전국","age_bracket":"55-64","campaign_name":"8LF_ASC_Detail_26.07.10","click_cvr_pct":"0.0","clicks":"3","cpa_krw":null,"cpc_krw":"1263150.0","cpm_krw":"1.3067068965517241E8","ctr_pct":"10.344827586206897","event_date":"2026-07-22","gender":"male","impressions":"29","purchases":"0","reach":"23","revenue":"0.0","roas":"0.0","spend_krw":"3789450.0"},{"ad_id":"120249962126230363","ad_name":"sale_promotion","adset_name":"25-55_여성_전국","age_bracket":"55-64","campaign_name":"8LF_ASC_Detail_26.07.10","click_cvr_pct":"0.0","clicks":"2","cpa_krw":null,"cpc_krw":"3066525.0","cpm_krw":"1.5332625E8","ctr_pct":"5.0","event_date":"2026-07-22","gender":"female","impressions":"40","purchases":"0","reach":"35","revenue":"0.0","roas":"0.0","spend_krw":"6133050.0"},{"ad_id":"120249962126230363","ad_name":"sale_promotion","adset_name":"25-55_여성_전국","age_bracket":"45-54","campaign_name":"8LF_ASC_Detail_26.07.10","click_cvr_pct":"0.0","clicks":"2","cpa_krw":null,"cpc_krw":"1275750.0","cpm_krw":"4.476315789473684E7","ctr_pct":"3.508771929824561","event_date":"2026-07-22","gender":"male","impressions":"57","purchases":"0","reach":"53","revenue":"0.0","roas":"0.0","spend_krw":"2551500.0"},{"ad_id":"120249962126230363","ad_name":"sale_promotion","adset_name":"25-55_여성_전국","age_bracket":"45-54","campaign_name":"8LF_ASC_Detail_26.07.10","click_cvr_pct":"0.0","clicks":"3","cpa_krw":null,"cpc_krw":"3097350.0","cpm_krw":"1.429546153846154E8","ctr_pct":"4.615384615384616","event_date":"2026-07-22","gender":"female","impressions":"65","purchases":"0","reach":"61","revenue":"0.0","roas":"0.0","spend_krw":"9292050.0"},{"ad_id":"120249962126230363","ad_name":"sale_promotion","adset_name":"25-55_여성_전국","age_bracket":"35-44","campaign_name":"8LF_ASC_Detail_26.07.10","click_cvr_pct":"0.0","clicks":"6","cpa_krw":null,"cpc_krw":"706275.0","cpm_krw":"5.105602409638554E7","ctr_pct":"7.228915662650602","event_date":"2026-07-22","gender":"male","impressions":"83","purchases":"0","reach":"73","revenue":"0.0","roas":"0.0","spend_krw":"4237650.0"},{"ad_id":"120249962126230363","ad_name":"sale_promotion","adset_name":"25-55_여성_전국","age_bracket":"35-44","campaign_name":"8LF_ASC_Detail_26.07.10","click_cvr_pct":"0.0","clicks":"6","cpa_krw":null,"cpc_krw":"1250775.0","cpm_krw":"8.62603448275862E7","ctr_pct":"6.896551724137931","event_date":"2026-07-22","gender":"female","impressions":"87","purchases":"0","reach":"81","revenue":"0.0","roas":"0.0","spend_krw":"7504650.0"},{"ad_id":"120249962126230363","ad_name":"sale_promotion","adset_name":"25-55_여성_전국","age_bracket":"25-34","campaign_name":"8LF_ASC_Detail_26.07.10","click_cvr_pct":null,"clicks":"0","cpa_krw":null,"cpc_krw":null,"cpm_krw":"7.309285714285715E7","ctr_pct":"0.0","event_date":"2026-07-22","gender":"male","impressions":"21","purchases":"0","reach":"21","revenue":"0.0","roas":"0.0","spend_krw":"1534950.0"},{"ad_id":"120249962126230363","ad_name":"sale_promotion","adset_name":"25-55_여성_전국","age_bracket":"25-34","campaign_name":"8LF_ASC_Detail_26.07.10","click_cvr_pct":"0.0","clicks":"2","cpa_krw":null,"cpc_krw":"1709100.0","cpm_krw":"9.766285714285715E7","ctr_pct":"5.714285714285714","event_date":"2026-07-22","gender":"female","impressions":"35","purchases":"0","reach":"35","revenue":"0.0","roas":"0.0","spend_krw":"3418200.0"},{"ad_id":"120249962126230363","ad_name":"sale_promotion","adset_name":"25-55_여성_전국","age_bracket":"18-24","campaign_name":"8LF_ASC_Detail_26.07.10","click_cvr_pct":null,"clicks":"0","cpa_krw":null,"cpc_krw":null,"cpm_krw":"4050000.0","ctr_pct":"0.0","event_date":"2026-07-22","gender":"unknown","impressions":"1","purchases":"0","reach":"1","revenue":"0.0","roas":"0.0","spend_krw":"4050.0"},{"ad_id":"120249962126230363","ad_name":"sale_promotion","adset_name":"25-55_여성_전국","age_bracket":"18-24","campaign_name":"8LF_ASC_Detail_26.07.10","click_cvr_pct":"0.0","clicks":"1","cpa_krw":null,"cpc_krw":"13500.0","cpm_krw":"1.35E7","ctr_pct":"100.0","event_date":"2026-07-22","gender":"male","impressions":"1","purchases":"0","reach":"1","revenue":"0.0","roas":"0.0","spend_krw":"13500.0"},{"ad_id":"120249962126230363","ad_name":"sale_promotion","adset_name":"25-55_여성_전국","age_bracket":"18-24","campaign_name":"8LF_ASC_Detail_26.07.10","click_cvr_pct":null,"clicks":"0","cpa_krw":null,"cpc_krw":null,"cpm_krw":"2.16E7","ctr_pct":"0.0","event_date":"2026-07-22","gender":"female","impressions":"5","purchases":"0","reach":"3","revenue":"0.0","roas":"0.0","spend_krw":"108000.0"},{"ad_id":"120249958733480363","ad_name":"Advantage+_MIX 26.07.10","adset_name":"8LF_ASC_MAIN 26.07.10","age_bracket":"65+","campaign_name":"8LF_ASC_CBO","click_cvr_pct":null,"clicks":"0","cpa_krw":null,"cpc_krw":null,"cpm_krw":"1.454625E8","ctr_pct":"0.0","event_date":"2026-07-22","gender":"male","impressions":"4","purchases":"0","reach":"4","revenue":"0.0","roas":"0.0","spend_krw":"581850.0"},{"ad_id":"120249958733480363","ad_name":"Advantage+_MIX 26.07.10","adset_name":"8LF_ASC_MAIN 26.07.10","age_bracket":"65+","campaign_name":"8LF_ASC_CBO","click_cvr_pct":"0.0","clicks":"1","cpa_krw":null,"cpc_krw":"1618650.0","cpm_krw":"1.0791E8","ctr_pct":"6.666666666666667","event_date":"2026-07-22","gender":"female","impressions":"15","purchases":"0","reach":"13","revenue":"0.0","roas":"0.0","spend_krw":"1618650.0"},{"ad_id":"120249958733480363","ad_name":"Advantage+_MIX 26.07.10","adset_name":"8LF_ASC_MAIN 26.07.10","age_bracket":"55-64","campaign_name":"8LF_ASC_CBO","click_cvr_pct":null,"clicks":"0","cpa_krw":null,"cpc_krw":null,"cpm_krw":"2.43E7","ctr_pct":"0.0","event_date":"2026-07-22","gender":"unknown","impressions":"2","purchases":"0","reach":"1","revenue":"0.0","roas":"0.0","spend_krw":"48600.0"},{"ad_id":"120249958733480363","ad_name":"Advantage+_MIX 26.07.10","adset_name":"8LF_ASC_MAIN 26.07.10","age_bracket":"55-64","campaign_name":"8LF_ASC_CBO","click_cvr_pct":null,"clicks":"0","cpa_krw":null,"cpc_krw":null,"cpm_krw":"1.2976530612244898E8","ctr_pct":"0.0","event_date":"2026-07-22","gender":"male","impressions":"49","purchases":"0","reach":"33","revenue":"0.0","roas":"0.0","spend_krw":"6358500.0"},{"ad_id":"120249958733480363","ad_name":"Advantage+_MIX 26.07.10","adset_name":"8LF_ASC_MAIN 26.07.10","age_bracket":"55-64","campaign_name":"8LF_ASC_CBO","click_cvr_pct":"0.0","clicks":"6","cpa_krw":null,"cpc_krw":"2681775.0","cpm_krw":"1.9155535714285713E8","ctr_pct":"7.142857142857142","event_date":"2026-07-22","gender":"female","impressions":"84","purchases":"0","reach":"68","revenue":"0.0","roas":"0.0","spend_krw":"1.609065E7"},{"ad_id":"120249958733480363","ad_name":"Advantage+_MIX 26.07.10","adset_name":"8LF_ASC_MAIN 26.07.10","age_bracket":"45-54","campaign_name":"8LF_ASC_CBO","click_cvr_pct":"0.0","clicks":"1","cpa_krw":null,"cpc_krw":"450900.0","cpm_krw":"1.12725E8","ctr_pct":"25.0","event_date":"2026-07-22","gender":"unknown","impressions":"4","purchases":"0","reach":"4","revenue":"0.0","roas":"0.0","spend_krw":"450900.0"},{"ad_id":"120249958733480363","ad_name":"Advantage+_MIX 26.07.10","adset_name":"8LF_ASC_MAIN 26.07.10","age_bracket":"45-54","campaign_name":"8LF_ASC_CBO","click_cvr_pct":"0.0","clicks":"3","cpa_krw":null,"cpc_krw":"2643300.0","cpm_krw":"7.080267857142857E7","ctr_pct":"2.6785714285714284","event_date":"2026-07-22","gender":"male","impressions":"112","purchases":"0","reach":"97","revenue":"0.0","roas":"0.0","spend_krw":"7929900.0"},{"ad_id":"120249958733480363","ad_name":"Advantage+_MIX 26.07.10","adset_name":"8LF_ASC_MAIN 26.07.10","age_bracket":"45-54","campaign_name":"8LF_ASC_CBO","click_cvr_pct":"0.0","clicks":"10","cpa_krw":null,"cpc_krw":"3589245.0","cpm_krw":"1.5273382978723404E8","ctr_pct":"4.25531914893617","event_date":"2026-07-22","gender":"female","impressions":"235","purchases":"0","reach":"209","revenue":"0.0","roas":"0.0","spend_krw":"3.589245E7"},{"ad_id":"120249958733480363","ad_name":"Advantage+_MIX 26.07.10","adset_name":"8LF_ASC_MAIN 26.07.10","age_bracket":"35-44","campaign_name":"8LF_ASC_CBO","click_cvr_pct":"150.0","clicks":"2","cpa_krw":"3297150.0","cpc_krw":"4945725.0","cpm_krw":"5.34672972972973E7","ctr_pct":"1.0810810810810811","event_date":"2026-07-22","gender":"male","impressions":"185","purchases":"3","reach":"160","revenue":"2.1384E8","roas":"21.6186706701242","spend_krw":"9891450.0"},{"ad_id":"120249958733480363","ad_name":"Advantage+_MIX 26.07.10","adset_name":"8LF_ASC_MAIN 26.07.10","age_bracket":"35-44","campaign_name":"8LF_ASC_CBO","click_cvr_pct":"66.66666666666666","clicks":"9","cpa_krw":"4925475.0","cpc_krw":"3283650.0","cpm_krw":"9.7857119205298E7","ctr_pct":"2.980132450331126","event_date":"2026-07-22","gender":"female","impressions":"302","purchases":"6","reach":"276","revenue":"4.2768E8","roas":"14.471700698917363","spend_krw":"2.955285E7"},{"ad_id":"120249958733480363","ad_name":"Advantage+_MIX 26.07.10","adset_name":"8LF_ASC_MAIN 26.07.10","age_bracket":"25-34","campaign_name":"8LF_ASC_CBO","click_cvr_pct":"0.0","clicks":"2","cpa_krw":null,"cpc_krw":"2168775.0","cpm_krw":"6.109225352112676E7","ctr_pct":"2.8169014084507045","event_date":"2026-07-22","gender":"male","impressions":"71","purchases":"0","reach":"64","revenue":"0.0","roas":"0.0","spend_krw":"4337550.0"},{"ad_id":"120249958733480363","ad_name":"Advantage+_MIX 26.07.10","adset_name":"8LF_ASC_MAIN 26.07.10","age_bracket":"25-34","campaign_name":"8LF_ASC_CBO","click_cvr_pct":"0.0","clicks":"3","cpa_krw":null,"cpc_krw":"3106800.0","cpm_krw":"6.904E7","ctr_pct":"2.2222222222222223","event_date":"2026-07-22","gender":"female","impressions":"135","purchases":"0","reach":"114","revenue":"0.0","roas":"0.0","spend_krw":"9320400.0"},{"ad_id":"120249958733480363","ad_name":"Advantage+_MIX 26.07.10","adset_name":"8LF_ASC_MAIN 26.07.10","age_bracket":"18-24","campaign_name":"8LF_ASC_CBO","click_cvr_pct":null,"clicks":"0","cpa_krw":null,"cpc_krw":null,"cpm_krw":"2.1195E7","ctr_pct":"0.0","event_date":"2026-07-22","gender":"male","impressions":"10","purchases":"0","reach":"9","revenue":"0.0","roas":"0.0","spend_krw":"211950.0"},{"ad_id":"120249958733480363","ad_name":"Advantage+_MIX 26.07.10","adset_name":"8LF_ASC_MAIN 26.07.10","age_bracket":"18-24","campaign_name":"8LF_ASC_CBO","click_cvr_pct":null,"clicks":"0","cpa_krw":null,"cpc_krw":null,"cpm_krw":"6.0075E7","ctr_pct":"0.0","event_date":"2026-07-22","gender":"female","impressions":"16","purchases":"0","reach":"15","revenue":"0.0","roas":"0.0","spend_krw":"961200.0"},{"ad_id":"120249958733480363","ad_name":"Advantage+_MIX 26.07.10","adset_name":"8LF_ASC_MAIN 26.07.10","age_bracket":"35-44","campaign_name":"8LF_ASC_CBO","click_cvr_pct":"11.538461538461538","clicks":"78","cpa_krw":"3.599055E7","cpc_krw":"4152755.769230769","cpm_krw":"1.2697567620540965E8","ctr_pct":"3.057624460995688","event_date":"2026-07-15","gender":"female","impressions":"2551","purchases":"9","reach":"1775","revenue":"5.9697E8","roas":"1.8429837832431013","spend_krw":"3.2391495E8"},{"ad_id":"120249962126230363","ad_name":"sale_promotion","adset_name":"25-55_여성_전국","age_bracket":"25-34","campaign_name":"8LF_ASC_Detail_26.07.10","click_cvr_pct":null,"clicks":"0","cpa_krw":null,"cpc_krw":null,"cpm_krw":"2.43E7","ctr_pct":"0.0","event_date":"2026-07-15","gender":"unknown","impressions":"1","purchases":"0","reach":"1","revenue":"0.0","roas":"0.0","spend_krw":"24300.0"},{"ad_id":"120249958733480363","ad_name":"Advantage+_MIX 26.07.10","adset_name":"8LF_ASC_MAIN 26.07.10","age_bracket":"25-34","campaign_name":"8LF_ASC_CBO","click_cvr_pct":"6.521739130434782","clicks":"46","cpa_krw":"4.571415E7","cpc_krw":"2981357.6086956523","cpm_krw":"1.067256420233463E8","ctr_pct":"3.5797665369649803","event_date":"2026-07-15","gender":"female","impressions":"1285","purchases":"3","reach":"757","revenue":"2.0169E8","roas":"1.470660616023704","spend_krw":"1.3714245E8"},{"ad_id":"120249958733480363","ad_name":"Advantage+_MIX 26.07.10","adset_name":"8LF_ASC_MAIN 26.07.10","age_bracket":"45-54","campaign_name":"8LF_ASC_CBO","click_cvr_pct":"15.18987341772152","clicks":"79","cpa_krw":"3.54061125E7","cpc_krw":"5378143.670886076","cpm_krw":"1.9347602459016395E8","ctr_pct":"3.5974499089253187","event_date":"2026-07-15","gender":"female","impressions":"2196","purchases":"12","reach":"1464","revenue":"8.1081E8","roas":"1.9083569256579638","spend_krw":"4.2487335E8"},{"ad_id":"120249958733480363","ad_name":"Advantage+_MIX 26.07.10","adset_name":"8LF_ASC_MAIN 26.07.10","age_bracket":"35-44","campaign_name":"8LF_ASC_CBO","click_cvr_pct":"15.789473684210526","clicks":"38","cpa_krw":"1.890225E7","cpc_krw":"2984565.789473684","cpm_krw":"8.489034431137724E7","ctr_pct":"2.844311377245509","event_date":"2026-07-15","gender":"male","impressions":"1336","purchases":"6","reach":"770","revenue":"4.0338E8","roas":"3.5567194381621237","spend_krw":"1.134135E8"},{"ad_id":"120249958733480363","ad_name":"Advantage+_MIX 26.07.10","adset_name":"8LF_ASC_MAIN 26.07.10","age_bracket":"65+","campaign_name":"8LF_ASC_CBO","click_cvr_pct":"0.0","clicks":"1","cpa_krw":null,"cpc_krw":"1.882845E7","cpm_krw":"2.8527954545454544E8","ctr_pct":"1.5151515151515151","event_date":"2026-07-15","gender":"male","impressions":"66","purchases":"0","reach":"46","revenue":"0.0","roas":"0.0","spend_krw":"1.882845E7"},{"ad_id":"120249958733480363","ad_name":"Advantage+_MIX 26.07.10","adset_name":"8LF_ASC_MAIN 26.07.10","age_bracket":"65+","campaign_name":"8LF_ASC_CBO","click_cvr_pct":"0.0","clicks":"8","cpa_krw":null,"cpc_krw":"6082931.25","cpm_krw":"2.79675E8","ctr_pct":"4.597701149425287","event_date":"2026-07-15","gender":"female","impressions":"174","purchases":"0","reach":"112","revenue":"0.0","roas":"0.0","spend_krw":"4.866345E7"},{"ad_id":"120249958733480363","ad_name":"Advantage+_MIX 26.07.10","adset_name":"8LF_ASC_MAIN 26.07.10","age_bracket":"55-64","campaign_name":"8LF_ASC_CBO","click_cvr_pct":"0.0","clicks":"17","cpa_krw":null,"cpc_krw":"2742008.8235294116","cpm_krw":"1.3750486725663716E8","ctr_pct":"5.014749262536873","event_date":"2026-07-15","gender":"male","impressions":"339","purchases":"0","reach":"200","revenue":"0.0","roas":"0.0","spend_krw":"4.661415E7"},{"ad_id":"120249958733480363","ad_name":"Advantage+_MIX 26.07.10","adset_name":"8LF_ASC_MAIN 26.07.10","age_bracket":"45-54","campaign_name":"8LF_ASC_CBO","click_cvr_pct":"0.0","clicks":"1","cpa_krw":null,"cpc_krw":"3103650.0","cpm_krw":"1.6335E8","ctr_pct":"5.263157894736842","event_date":"2026-07-15","gender":"unknown","impressions":"19","purchases":"0","reach":"11","revenue":"0.0","roas":"0.0","spend_krw":"3103650.0"},{"ad_id":"120249958733480363","ad_name":"Advantage+_MIX 26.07.10","adset_name":"8LF_ASC_MAIN 26.07.10","age_bracket":"45-54","campaign_name":"8LF_ASC_CBO","click_cvr_pct":"0.0","clicks":"34","cpa_krw":null,"cpc_krw":"3125170.588235294","cpm_krw":"1.1965743243243243E8","ctr_pct":"3.8288288288288284","event_date":"2026-07-15","gender":"male","impressions":"888","purchases":"0","reach":"553","revenue":"0.0","roas":"0.0","spend_krw":"1.062558E8"},{"ad_id":"120249958733480363","ad_name":"Advantage+_MIX 26.07.10","adset_name":"8LF_ASC_MAIN 26.07.10","age_bracket":"25-34","campaign_name":"8LF_ASC_CBO","click_cvr_pct":"0.0","clicks":"7","cpa_krw":null,"cpc_krw":"5049964.285714285","cpm_krw":"5.472097523219814E7","ctr_pct":"1.08359133126935","event_date":"2026-07-15","gender":"male","impressions":"646","purchases":"0","reach":"423","revenue":"0.0","roas":"0.0","spend_krw":"3.534975E7"},{"ad_id":"120249958733480363","ad_name":"Advantage+_MIX 26.07.10","adset_name":"8LF_ASC_MAIN 26.07.10","age_bracket":"18-24","campaign_name":"8LF_ASC_CBO","click_cvr_pct":"0.0","clicks":"5","cpa_krw":null,"cpc_krw":"997650.0","cpm_krw":"5.668465909090909E7","ctr_pct":"5.681818181818182","event_date":"2026-07-15","gender":"male","impressions":"88","purchases":"0","reach":"48","revenue":"0.0","roas":"0.0","spend_krw":"4988250.0"},{"ad_id":"120249958733480363","ad_name":"Advantage+_MIX 26.07.10","adset_name":"8LF_ASC_MAIN 26.07.10","age_bracket":"18-24","campaign_name":"8LF_ASC_CBO","click_cvr_pct":"0.0","clicks":"3","cpa_krw":null,"cpc_krw":"5717250.0","cpm_krw":"1.128404605263158E8","ctr_pct":"1.9736842105263157","event_date":"2026-07-15","gender":"female","impressions":"152","purchases":"0","reach":"98","revenue":"0.0","roas":"0.0","spend_krw":"1.715175E7"},{"ad_id":"120249958733480363","ad_name":"Advantage+_MIX 26.07.10","adset_name":"8LF_ASC_MAIN 26.07.10","age_bracket":"55-64","campaign_name":"8LF_ASC_CBO","click_cvr_pct":null,"clicks":"0","cpa_krw":null,"cpc_krw":null,"cpm_krw":"1.6965E8","ctr_pct":"0.0","event_date":"2026-07-15","gender":"unknown","impressions":"6","purchases":"0","reach":"5","revenue":"0.0","roas":"0.0","spend_krw":"1017900.0"},{"ad_id":"120249958733480363","ad_name":"Advantage+_MIX 26.07.10","adset_name":"8LF_ASC_MAIN 26.07.10","age_bracket":"35-44","campaign_name":"8LF_ASC_CBO","click_cvr_pct":null,"clicks":"0","cpa_krw":null,"cpc_krw":null,"cpm_krw":"9.019038461538461E7","ctr_pct":"0.0","event_date":"2026-07-15","gender":"unknown","impressions":"26","purchases":"0","reach":"17","revenue":"0.0","roas":"0.0","spend_krw":"2344950.0"},{"ad_id":"120249958733480363","ad_name":"Advantage+_MIX 26.07.10","adset_name":"8LF_ASC_MAIN 26.07.10","age_bracket":"25-34","campaign_name":"8LF_ASC_CBO","click_cvr_pct":null,"clicks":"0","cpa_krw":null,"cpc_krw":null,"cpm_krw":"1.965E7","ctr_pct":"0.0","event_date":"2026-07-15","gender":"unknown","impressions":"9","purchases":"0","reach":"8","revenue":"0.0","roas":"0.0","spend_krw":"176850.0"},{"ad_id":"120249958733480363","ad_name":"Advantage+_MIX 26.07.10","adset_name":"8LF_ASC_MAIN 26.07.10","age_bracket":"18-24","campaign_name":"8LF_ASC_CBO","click_cvr_pct":null,"clicks":"0","cpa_krw":null,"cpc_krw":null,"cpm_krw":"4050000.0","ctr_pct":"0.0","event_date":"2026-07-15","gender":"unknown","impressions":"2","purchases":"0","reach":"2","revenue":"0.0","roas":"0.0","spend_krw":"8100.0"},{"ad_id":"120249962126230363","ad_name":"sale_promotion","adset_name":"25-55_여성_전국","age_bracket":"35-44","campaign_name":"8LF_ASC_Detail_26.07.10","click_cvr_pct":"19.565217391304348","clicks":"46","cpa_krw":"8518200.0","cpc_krw":"1666604.347826087","cpm_krw":"8.771601830663615E7","ctr_pct":"5.263157894736842","event_date":"2026-07-15","gender":"female","impressions":"874","purchases":"9","reach":"721","revenue":"6.4152E8","roas":"8.367965063041488","spend_krw":"7.66638E7"},{"ad_id":"120249962126230363","ad_name":"sale_promotion","adset_name":"25-55_여성_전국","age_bracket":"35-44","campaign_name":"8LF_ASC_Detail_26.07.10","click_cvr_pct":"8.108108108108109","clicks":"37","cpa_krw":"1.617885E7","cpc_krw":"1311798.6486486488","cpm_krw":"6.993739193083574E7","ctr_pct":"5.3314121037463975","event_date":"2026-07-15","gender":"male","impressions":"694","purchases":"3","reach":"488","revenue":"2.0169E8","roas":"4.155425138375101","spend_krw":"4.853655E7"},{"ad_id":"120249962126230363","ad_name":"sale_promotion","adset_name":"25-55_여성_전국","age_bracket":"45-54","campaign_name":"8LF_ASC_Detail_26.07.10","click_cvr_pct":"3.896103896103896","clicks":"77","cpa_krw":"4.33899E7","cpc_krw":"1690515.5844155843","cpm_krw":"1.3108731117824773E8","ctr_pct":"7.754279959718026","event_date":"2026-07-15","gender":"female","impressions":"993","purchases":"3","reach":"832","revenue":"2.1384E8","roas":"1.642778618987368","spend_krw":"1.301697E8"},{"ad_id":"120249962126230363","ad_name":"sale_promotion","adset_name":"25-55_여성_전국","age_bracket":"65+","campaign_name":"8LF_ASC_Detail_26.07.10","click_cvr_pct":"0.0","clicks":"6","cpa_krw":null,"cpc_krw":"2085075.0","cpm_krw":"1.9547578125E8","ctr_pct":"9.375","event_date":"2026-07-15","gender":"male","impressions":"64","purchases":"0","reach":"45","revenue":"0.0","roas":"0.0","spend_krw":"1.251045E7"},{"ad_id":"120249962126230363","ad_name":"sale_promotion","adset_name":"25-55_여성_전국","age_bracket":"65+","campaign_name":"8LF_ASC_Detail_26.07.10","click_cvr_pct":"0.0","clicks":"8","cpa_krw":null,"cpc_krw":"1664550.0","cpm_krw":"1.929913043478261E8","ctr_pct":"11.594202898550725","event_date":"2026-07-15","gender":"female","impressions":"69","purchases":"0","reach":"56","revenue":"0.0","roas":"0.0","spend_krw":"1.33164E7"},{"ad_id":"120249962126230363","ad_name":"sale_promotion","adset_name":"25-55_여성_전국","age_bracket":"55-64","campaign_name":"8LF_ASC_Detail_26.07.10","click_cvr_pct":"0.0","clicks":"25","cpa_krw":null,"cpc_krw":"1217754.0","cpm_krw":"9.884366883116883E7","ctr_pct":"8.116883116883116","event_date":"2026-07-15","gender":"male","impressions":"308","purchases":"0","reach":"203","revenue":"0.0","roas":"0.0","spend_krw":"3.044385E7"},{"ad_id":"120249962126230363","ad_name":"sale_promotion","adset_name":"25-55_여성_전국","age_bracket":"55-64","campaign_name":"8LF_ASC_Detail_26.07.10","click_cvr_pct":"0.0","clicks":"25","cpa_krw":null,"cpc_krw":"2307960.0","cpm_krw":"1.682186588921283E8","ctr_pct":"7.288629737609329","event_date":"2026-07-15","gender":"female","impressions":"343","purchases":"0","reach":"300","revenue":"0.0","roas":"0.0","spend_krw":"5.7699E7"},{"ad_id":"120249962126230363","ad_name":"sale_promotion","adset_name":"25-55_여성_전국","age_bracket":"45-54","campaign_name":"8LF_ASC_Detail_26.07.10","click_cvr_pct":"0.0","clicks":"34","cpa_krw":null,"cpc_krw":"1663200.0","cpm_krw":"8.821965678627145E7","ctr_pct":"5.30421216848674","event_date":"2026-07-15","gender":"male","impressions":"641","purchases":"0","reach":"504","revenue":"0.0","roas":"0.0","spend_krw":"5.65488E7"},{"ad_id":"120249962126230363","ad_name":"sale_promotion","adset_name":"25-55_여성_전국","age_bracket":"25-34","campaign_name":"8LF_ASC_Detail_26.07.10","click_cvr_pct":"0.0","clicks":"2","cpa_krw":null,"cpc_krw":"3844800.0","cpm_krw":"4.1791304347826086E7","ctr_pct":"1.0869565217391304","event_date":"2026-07-15","gender":"male","impressions":"184","purchases":"0","reach":"147","revenue":"0.0","roas":"0.0","spend_krw":"7689600.0"},{"ad_id":"120249962126230363","ad_name":"sale_promotion","adset_name":"25-55_여성_전국","age_bracket":"25-34","campaign_name":"8LF_ASC_Detail_26.07.10","click_cvr_pct":"0.0","clicks":"14","cpa_krw":null,"cpc_krw":"1712185.7142857143","cpm_krw":"7.682884615384616E7","ctr_pct":"4.487179487179487","event_date":"2026-07-15","gender":"female","impressions":"312","purchases":"0","reach":"232","revenue":"0.0","roas":"0.0","spend_krw":"2.39706E7"},{"ad_id":"120249962126230363","ad_name":"sale_promotion","adset_name":"25-55_여성_전국","age_bracket":"18-24","campaign_name":"8LF_ASC_Detail_26.07.10","click_cvr_pct":"0.0","clicks":"1","cpa_krw":null,"cpc_krw":"1999350.0","cpm_krw":"5.880441176470588E7","ctr_pct":"2.941176470588235","event_date":"2026-07-15","gender":"male","impressions":"34","purchases":"0","reach":"21","revenue":"0.0","roas":"0.0","spend_krw":"1999350.0"},{"ad_id":"120249962126230363","ad_name":"sale_promotion","adset_name":"25-55_여성_전국","age_bracket":"18-24","campaign_name":"8LF_ASC_Detail_26.07.10","click_cvr_pct":"0.0","clicks":"2","cpa_krw":null,"cpc_krw":"795150.0","cpm_krw":"3.614318181818182E7","ctr_pct":"4.545454545454546","event_date":"2026-07-15","gender":"female","impressions":"44","purchases":"0","reach":"38","revenue":"0.0","roas":"0.0","spend_krw":"1590300.0"},{"ad_id":"120249962126230363","ad_name":"sale_promotion","adset_name":"25-55_여성_전국","age_bracket":"45-54","campaign_name":"8LF_ASC_Detail_26.07.10","click_cvr_pct":null,"clicks":"0","cpa_krw":null,"cpc_krw":null,"cpm_krw":"7.86375E7","ctr_pct":"0.0","event_date":"2026-07-15","gender":"unknown","impressions":"8","purchases":"0","reach":"7","revenue":"0.0","roas":"0.0","spend_krw":"629100.0"},{"ad_id":"120249962126230363","ad_name":"sale_promotion","adset_name":"25-55_여성_전국","age_bracket":"35-44","campaign_name":"8LF_ASC_Detail_26.07.10","click_cvr_pct":null,"clicks":"0","cpa_krw":null,"cpc_krw":null,"cpm_krw":"1.103625E8","ctr_pct":"0.0","event_date":"2026-07-15","gender":"unknown","impressions":"4","purchases":"0","reach":"3","revenue":"0.0","roas":"0.0","spend_krw":"441450.0"},{"ad_id":"120249958733480363","ad_name":"Advantage+_MIX 26.07.10","adset_name":"8LF_ASC_MAIN 26.07.10","age_bracket":"55-64","campaign_name":"8LF_ASC_CBO","click_cvr_pct":"8.108108108108109","clicks":"37","cpa_krw":"6.23034E7","cpc_krw":"5051627.027027027","cpm_krw":"2.6739656652360514E8","ctr_pct":"5.293276108726753","event_date":"2026-07-15","gender":"female","impressions":"699","purchases":"3","reach":"506","revenue":"2.1384E8","roas":"1.1440788143183198","spend_krw":"1.869102E8"}]
